numscan/__init__.py
numscan/all.py
numscan/base.py
numscan/date.py
numscan/fibonacci.py
numscan/popculture.py
numscan/prime.py
numscan/squares.py
numscan-0.1.6.dist-info/licenses/LICENSE
numscan-0.1.6.dist-info/METADATA
numscan-0.1.6.dist-info/WHEEL
numscan-0.1.6.dist-info/top_level.txt
numscan-0.1.6.dist-info/RECORD
