Metadata-Version: 2.4
Name: numscan
Version: 0.1.6
Summary: Count interesting number patterns in text files
Author: Christian Rabenstein
Requires-Python: >=3.9
License-File: LICENSE
Dynamic: license-file
